pendragondi_api_pro/__init__.py
pendragondi_api_pro/__main__.py
pendragondi_api_pro/core.py
pendragondi_api_pro/export.py
pendragondi_api_pro/redact.py
pendragondi_api_pro-1.0.3.dist-info/licenses/LICENSE
pendragondi_api_pro-1.0.3.dist-info/METADATA
pendragondi_api_pro-1.0.3.dist-info/WHEEL
pendragondi_api_pro-1.0.3.dist-info/top_level.txt
pendragondi_api_pro-1.0.3.dist-info/RECORD
