Metadata-Version: 2.4
Name: pendragondi-api-pro
Version: 1.0.3
Summary: PendragoniDI API Pro: Context-rich duplicate detection (non-AI)
Author-email: JinPendragon <pendragondi@pendragondi.dev>
License: MIT
Classifier: Programming Language :: Python :: 3
Classifier: License :: OSI Approved :: MIT License
Classifier: Operating System :: OS Independent
Requires-Python: >=3.8
License-File: LICENSE
Dynamic: license-file
